README.md
setup.py
blockchain_etl_common_instrumented.egg-info/PKG-INFO
blockchain_etl_common_instrumented.egg-info/SOURCES.txt
blockchain_etl_common_instrumented.egg-info/dependency_links.txt
blockchain_etl_common_instrumented.egg-info/requires.txt
blockchain_etl_common_instrumented.egg-info/top_level.txt
blockchainetl_common/__init__.py
blockchainetl_common/atomic_counter.py
blockchainetl_common/csv_utils.py
blockchainetl_common/exporters.py
blockchainetl_common/file_utils.py
blockchainetl_common/logging_utils.py
blockchainetl_common/progress_logger.py
blockchainetl_common/thread_local_proxy.py
blockchainetl_common/utils.py
blockchainetl_common/executors/__init__.py
blockchainetl_common/executors/batch_work_executor.py
blockchainetl_common/executors/bounded_executor.py
blockchainetl_common/executors/fail_safe_executor.py
blockchainetl_common/executors/retriable_value_error.py
blockchainetl_common/graph/__init__.py
blockchainetl_common/graph/graph_operations.py
blockchainetl_common/jobs/__init__.py
blockchainetl_common/jobs/base_job.py
blockchainetl_common/jobs/exporters/__init__.py
blockchainetl_common/jobs/exporters/composite_item_exporter.py
blockchainetl_common/jobs/exporters/console_item_exporter.py
blockchainetl_common/jobs/exporters/gcs_item_exporter.py
blockchainetl_common/jobs/exporters/google_pubsub_item_exporter.py
blockchainetl_common/jobs/exporters/in_memory_item_exporter.py
blockchainetl_common/jobs/exporters/multi_item_exporter.py
blockchainetl_common/streaming/__init__.py
blockchainetl_common/streaming/streamer.py
blockchainetl_common/streaming/streamer_adapter_stub.py
blockchainetl_common/streaming/streaming_utils.py