Metadata-Version: 2.1
Name: blockchain-etl-common-instrumented
Version: 1.6.2a1
Summary: Common utils for Blockchain ETL
Home-page: https://github.com/blockchain-etl/blockchain-etl-common
Author: Evgeny Medvedev
Author-email: evge.medvedev@gmail.com
Maintainer: Richard Mah
Maintainer-email: richard@geometrylabs.io
License: UNKNOWN
Project-URL: Bug Reports, https://github.com/geometry-labs/blockchain-etl-common/issues
Project-URL: Source, https://github.com/geometry-labs/blockchain-etl-common
Keywords: blockchain ethereum bitcoin etl
Platform: UNKNOWN
Classifier: Development Status :: 5 - Production/Stable
Classifier: Intended Audience :: Developers
Classifier: License :: OSI Approved :: MIT License
Classifier: Programming Language :: Python :: 3
Classifier: Programming Language :: Python :: 3.5
Classifier: Programming Language :: Python :: 3.6
Classifier: Programming Language :: Python :: 3.7
Requires-Python: >=3.5.3,<4
Provides-Extra: streaming
